drf_auto_query/__init__.py
drf_auto_query/exceptions.py
drf_auto_query/field_tree_builder.py
drf_auto_query/mixins.py
drf_auto_query/query_builder.py
drf_auto_query/types.py
drf_auto_query/utils.py
drf_auto_query-0.1.0.dist-info/LICENSE
drf_auto_query-0.1.0.dist-info/WHEEL
drf_auto_query-0.1.0.dist-info/METADATA
drf_auto_query-0.1.0.dist-info/RECORD
